<?xml version="1.0"?>
<xbrl xmlns="http://www.xbrl.org/2003/instance" xmlns:xbrli="http://www.xbrl.org/2003/instance" xmlns:link="http://www.xbrl.org/2003/linkbase" xmlns:xlink="http://www.w3.org/1999/xlink" xmlns:iso4217="http://www.xbrl.org/2003/iso4217" xmlns:tw-tse-pt="http://www.tse.com.tw/tw/fr/gaap/2008-12-20"><link:schemaRef xlink:type="simple" xlink:arcrole="http://www.w3.org/1999/xlink/properties/linkbase" xlink:href="tw-tse-pt_2008-12-20.xsd"/><tw-tse-pt:CashCashEquivalents contextRef="AsOf20040630" unitRef="TWD" decimals="-3">10293459000</tw-tse-pt:CashCashEquivalents><tw-tse-pt:NetNotesReceivable contextRef="AsOf20040630" unitRef="TWD" decimals="-3">62698000</tw-tse-pt:NetNotesReceivable><tw-tse-pt:NetAccountsReceivable contextRef="AsOf20040630" unitRef="TWD" decimals="-3">10913022000</tw-tse-pt:NetAccountsReceivable><tw-tse-pt:NetAccountsReceivableRelatedParties contextRef="AsOf20040630" unitRef="TWD" decimals="-3">18554034000</tw-tse-pt:NetAccountsReceivableRelatedParties><tw-tse-pt:InventoriesManufacturing contextRef="AsOf20040630" unitRef="TWD" decimals="-3">5549812000</tw-tse-pt:InventoriesManufacturing><tw-tse-pt:Inventories contextRef="AsOf20040630" unitRef="TWD" decimals="-3">5549812000</tw-tse-pt:Inventories><tw-tse-pt:OtherCurrentAssets contextRef="AsOf20040630" unitRef="TWD" decimals="-3">1945096000</tw-tse-pt:OtherCurrentAssets><tw-tse-pt:CurrentAssets contextRef="AsOf20040630" unitRef="TWD" decimals="-3">47318121000</tw-tse-pt:CurrentAssets><tw-tse-pt:FundsInvestments contextRef="AsOf20040630" unitRef="TWD" decimals="-3">32028580000</tw-tse-pt:FundsInvestments><tw-tse-pt:Land contextRef="AsOf20040630" unitRef="TWD" decimals="-3">1182384000</tw-tse-pt:Land><tw-tse-pt:BuildingsStructures contextRef="AsOf20040630" unitRef="TWD" decimals="-3">1499543000</tw-tse-pt:BuildingsStructures><tw-tse-pt:MachineryEquipment contextRef="AsOf20040630" unitRef="TWD" decimals="-3">2494161000</tw-tse-pt:MachineryEquipment><tw-tse-pt:MoldingEquipment contextRef="AsOf20040630" unitRef="TWD" decimals="-3">352498000</tw-tse-pt:MoldingEquipment><tw-tse-pt:TransportationEquipment contextRef="AsOf20040630" unitRef="TWD" decimals="-3">44298000</tw-tse-pt:TransportationEquipment><tw-tse-pt:OfficeEquipment contextRef="AsOf20040630" unitRef="TWD" decimals="-3">675413000</tw-tse-pt:OfficeEquipment><tw-tse-pt:OtherFacilities contextRef="AsOf20040630" unitRef="TWD" decimals="-3">916153000</tw-tse-pt:OtherFacilities><tw-tse-pt:FixedAssetsOriginalCosts contextRef="AsOf20040630" unitRef="TWD" decimals="-3">7164450000</tw-tse-pt:FixedAssetsOriginalCosts><tw-tse-pt:AccumulatedDepreciation contextRef="AsOf20040630" unitRef="TWD" decimals="-3">-3529740000</tw-tse-pt:AccumulatedDepreciation><tw-tse-pt:ConstructionProcessPrepaymentEquipments contextRef="AsOf20040630" unitRef="TWD" decimals="-3">243908000</tw-tse-pt:ConstructionProcessPrepaymentEquipments><tw-tse-pt:FixedAssets contextRef="AsOf20040630" unitRef="TWD" decimals="-3">3878618000</tw-tse-pt:FixedAssets><tw-tse-pt:Patents contextRef="AsOf20040630" unitRef="TWD" decimals="-3">0</tw-tse-pt:Patents><tw-tse-pt:Goodwill contextRef="AsOf20040630" unitRef="TWD" decimals="-3">199186000</tw-tse-pt:Goodwill><tw-tse-pt:IntangibleAssets contextRef="AsOf20040630" unitRef="TWD" decimals="-3">199186000</tw-tse-pt:IntangibleAssets><tw-tse-pt:RentalAssets contextRef="AsOf20040630" unitRef="TWD" decimals="-3">57154000</tw-tse-pt:RentalAssets><tw-tse-pt:IdledAssets contextRef="AsOf20040630" unitRef="TWD" decimals="-3">135311000</tw-tse-pt:IdledAssets><tw-tse-pt:GuaranteeDepositsPaid contextRef="AsOf20040630" unitRef="TWD" decimals="-3">40085000</tw-tse-pt:GuaranteeDepositsPaid><tw-tse-pt:DeferredCharges contextRef="AsOf20040630" unitRef="TWD" decimals="-3">724513000</tw-tse-pt:DeferredCharges><tw-tse-pt:OtherAssetsOther contextRef="AsOf20040630" unitRef="TWD" decimals="-3">31000</tw-tse-pt:OtherAssetsOther><tw-tse-pt:OtherAssets contextRef="AsOf20040630" unitRef="TWD" decimals="-3">957094000</tw-tse-pt:OtherAssets><tw-tse-pt:Assets contextRef="AsOf20040630" unitRef="TWD" decimals="-3">84381599000</tw-tse-pt:Assets><tw-tse-pt:ShortTermBorrowings contextRef="AsOf20040630" unitRef="TWD" decimals="-3">9608988000</tw-tse-pt:ShortTermBorrowings><tw-tse-pt:NotesPayable contextRef="AsOf20040630" unitRef="TWD" decimals="-3">46843000</tw-tse-pt:NotesPayable><tw-tse-pt:AccountsPayable contextRef="AsOf20040630" unitRef="TWD" decimals="-3">9624253000</tw-tse-pt:AccountsPayable><tw-tse-pt:AccountsPayableRelatedParties contextRef="AsOf20040630" unitRef="TWD" decimals="-3">6903419000</tw-tse-pt:AccountsPayableRelatedParties><tw-tse-pt:IncomeTaxPayable contextRef="AsOf20040630" unitRef="TWD" decimals="-3">352949000</tw-tse-pt:IncomeTaxPayable><tw-tse-pt:AccruedExpenses contextRef="AsOf20040630" unitRef="TWD" decimals="-3">2499369000</tw-tse-pt:AccruedExpenses><tw-tse-pt:OtherPayables contextRef="AsOf20040630" unitRef="TWD" decimals="-3">3124297000</tw-tse-pt:OtherPayables><tw-tse-pt:LongTermLiabilitiesCurrentPortion contextRef="AsOf20040630" unitRef="TWD" decimals="-3">100000000</tw-tse-pt:LongTermLiabilitiesCurrentPortion><tw-tse-pt:OtherCurrentLiabilities contextRef="AsOf20040630" unitRef="TWD" decimals="-3">2427238000</tw-tse-pt:OtherCurrentLiabilities><tw-tse-pt:CurrentLiabilities contextRef="AsOf20040630" unitRef="TWD" decimals="-3">34687356000</tw-tse-pt:CurrentLiabilities><tw-tse-pt:LongTermLiabilities contextRef="AsOf20040630" unitRef="TWD" decimals="-3">4150000000</tw-tse-pt:LongTermLiabilities><tw-tse-pt:ReserveLandRevaluationIncrementTax contextRef="AsOf20040630" unitRef="TWD" decimals="-3">145433000</tw-tse-pt:ReserveLandRevaluationIncrementTax><tw-tse-pt:Reserves contextRef="AsOf20040630" unitRef="TWD" decimals="-3">145433000</tw-tse-pt:Reserves><tw-tse-pt:PensionReserve contextRef="AsOf20040630" unitRef="TWD" decimals="-3">65057000</tw-tse-pt:PensionReserve><tw-tse-pt:DeferredIncomeTax contextRef="AsOf20040630" unitRef="TWD" decimals="-3">275254000</tw-tse-pt:DeferredIncomeTax><tw-tse-pt:OtherLiabilitiesOther contextRef="AsOf20040630" unitRef="TWD" decimals="-3">176737000</tw-tse-pt:OtherLiabilitiesOther><tw-tse-pt:OtherLiabilities contextRef="AsOf20040630" unitRef="TWD" decimals="-3">517048000</tw-tse-pt:OtherLiabilities><tw-tse-pt:Liabilities contextRef="AsOf20040630" unitRef="TWD" decimals="-3">39499837000</tw-tse-pt:Liabilities><tw-tse-pt:CommonStock contextRef="AsOf20040630" unitRef="TWD" decimals="-3">22405656000</tw-tse-pt:CommonStock><tw-tse-pt:StockDividendDistributed contextRef="AsOf20040630" unitRef="TWD" decimals="-3">2715794000</tw-tse-pt:StockDividendDistributed><tw-tse-pt:CapitalStock contextRef="AsOf20040630" unitRef="TWD" decimals="-3">25121450000</tw-tse-pt:CapitalStock><tw-tse-pt:CapitalSurplusAdditionalPaidCapital contextRef="AsOf20040630" unitRef="TWD" decimals="-3">5214561000</tw-tse-pt:CapitalSurplusAdditionalPaidCapital><tw-tse-pt:CapitalSurplusTreasuryStockTransactions contextRef="AsOf20040630" unitRef="TWD" decimals="-3">142994000</tw-tse-pt:CapitalSurplusTreasuryStockTransactions><tw-tse-pt:CapitalSurplusLongTermEquityInvestments contextRef="AsOf20040630" unitRef="TWD" decimals="-3">104777000</tw-tse-pt:CapitalSurplusLongTermEquityInvestments><tw-tse-pt:CapitalSurplusPremiumMerger contextRef="AsOf20040630" unitRef="TWD" decimals="-3">10292444000</tw-tse-pt:CapitalSurplusPremiumMerger><tw-tse-pt:CapitalSurplus contextRef="AsOf20040630" unitRef="TWD" decimals="-3">15754776000</tw-tse-pt:CapitalSurplus><tw-tse-pt:LegalReserve contextRef="AsOf20040630" unitRef="TWD" decimals="-3">1789456000</tw-tse-pt:LegalReserve><tw-tse-pt:UnappropriatedRetainedEarnings contextRef="AsOf20040630" unitRef="TWD" decimals="-3">3972665000</tw-tse-pt:UnappropriatedRetainedEarnings><tw-tse-pt:RetainedEarnings contextRef="AsOf20040630" unitRef="TWD" decimals="-3">6284503000</tw-tse-pt:RetainedEarnings><tw-tse-pt:SpecialReserve contextRef="AsOf20040630" unitRef="TWD" decimals="-3">522382000</tw-tse-pt:SpecialReserve><tw-tse-pt:UnrealizedValuationLossesLongTermEquityInvestment contextRef="AsOf20040630" unitRef="TWD" decimals="-3">-412079000</tw-tse-pt:UnrealizedValuationLossesLongTermEquityInvestment><tw-tse-pt:CumulativeTranslationAdjustments contextRef="AsOf20040630" unitRef="TWD" decimals="-3">-159965000</tw-tse-pt:CumulativeTranslationAdjustments><tw-tse-pt:StockholdersEquitiesAdjustments contextRef="AsOf20040630" unitRef="TWD" decimals="-3">-572044000</tw-tse-pt:StockholdersEquitiesAdjustments><tw-tse-pt:TreasuryStock contextRef="AsOf20040630" unitRef="TWD" decimals="-3">-1706923000</tw-tse-pt:TreasuryStock><tw-tse-pt:StockholdersEquities contextRef="AsOf20040630" unitRef="TWD" decimals="-3">44881762000</tw-tse-pt:StockholdersEquities><tw-tse-pt:OperatingIncome contextRef="From20040101To20040630" unitRef="TWD" decimals="-3">70278439000</tw-tse-pt:OperatingIncome><tw-tse-pt:NetSales contextRef="From20040101To20040630" unitRef="TWD" decimals="-3">70278439000</tw-tse-pt:NetSales><tw-tse-pt:Sales contextRef="From20040101To20040630" unitRef="TWD" decimals="-3">70607532000</tw-tse-pt:Sales><tw-tse-pt:SalesReturns contextRef="From20040101To20040630" unitRef="TWD" decimals="-3">175399000</tw-tse-pt:SalesReturns><tw-tse-pt:SalesDiscountsAllowances contextRef="From20040101To20040630" unitRef="TWD" decimals="-3">153694000</tw-tse-pt:SalesDiscountsAllowances><tw-tse-pt:OperatingCosts contextRef="From20040101To20040630" unitRef="TWD" decimals="-3">64553955000</tw-tse-pt:OperatingCosts><tw-tse-pt:GrossProfitLossOperations contextRef="From20040101To20040630" unitRef="TWD" decimals="-3">5724484000</tw-tse-pt:GrossProfitLossOperations><tw-tse-pt:RealizedGainInterAffiliateAccounts contextRef="From20040101To20040630" unitRef="TWD" decimals="-3">9827000</tw-tse-pt:RealizedGainInterAffiliateAccounts><tw-tse-pt:Sellingexpense contextRef="From20040101To20040630" unitRef="TWD" decimals="-3">1705203000</tw-tse-pt:Sellingexpense><tw-tse-pt:GeneralAdministrativeExpenses contextRef="From20040101To20040630" unitRef="TWD" decimals="-3">858623000</tw-tse-pt:GeneralAdministrativeExpenses><tw-tse-pt:ResearchDevelopmentExpenses contextRef="From20040101To20040630" unitRef="TWD" decimals="-3">951429000</tw-tse-pt:ResearchDevelopmentExpenses><tw-tse-pt:OperatingExpenses contextRef="From20040101To20040630" unitRef="TWD" decimals="-3">3515255000</tw-tse-pt:OperatingExpenses><tw-tse-pt:OperatingIncomeLoss contextRef="From20040101To20040630" unitRef="TWD" decimals="-3">2219056000</tw-tse-pt:OperatingIncomeLoss><tw-tse-pt:InterestIncome contextRef="From20040101To20040630" unitRef="TWD" decimals="-3">8110000</tw-tse-pt:InterestIncome><tw-tse-pt:InvestmentIncomes contextRef="From20040101To20040630" unitRef="TWD" decimals="-3">1831579000</tw-tse-pt:InvestmentIncomes><tw-tse-pt:GainsSaleInvestments contextRef="From20040101To20040630" unitRef="TWD" decimals="-3">512822000</tw-tse-pt:GainsSaleInvestments><tw-tse-pt:ForeignExchangeGains contextRef="From20040101To20040630" unitRef="TWD" decimals="-3">0</tw-tse-pt:ForeignExchangeGains><tw-tse-pt:IncomeSaleScrapWaste contextRef="From20040101To20040630" unitRef="TWD" decimals="-3">0</tw-tse-pt:IncomeSaleScrapWaste><tw-tse-pt:GainsInventoryValueRecoveries contextRef="From20040101To20040630" unitRef="TWD" decimals="-3">0</tw-tse-pt:GainsInventoryValueRecoveries><tw-tse-pt:MiscellaneousIncome contextRef="From20040101To20040630" unitRef="TWD" decimals="-3">188338000</tw-tse-pt:MiscellaneousIncome><tw-tse-pt:NonOperatingRevenuesGains contextRef="From20040101To20040630" unitRef="TWD" decimals="-3">2540849000</tw-tse-pt:NonOperatingRevenuesGains><tw-tse-pt:InterestExpense contextRef="From20040101To20040630" unitRef="TWD" decimals="-3">112600000</tw-tse-pt:InterestExpense><tw-tse-pt:LossPhysicalInventory contextRef="From20040101To20040630" unitRef="TWD" decimals="-3">50722000</tw-tse-pt:LossPhysicalInventory><tw-tse-pt:ForeignExchangeLosses contextRef="From20040101To20040630" unitRef="TWD" decimals="-3">128870000</tw-tse-pt:ForeignExchangeLosses><tw-tse-pt:LossInventoryValuationObsolescence contextRef="From20040101To20040630" unitRef="TWD" decimals="-3">69604000</tw-tse-pt:LossInventoryValuationObsolescence><tw-tse-pt:MiscellaneousDisbursements contextRef="From20040101To20040630" unitRef="TWD" decimals="-3">274666000</tw-tse-pt:MiscellaneousDisbursements><tw-tse-pt:NonOperatingExpenses contextRef="From20040101To20040630" unitRef="TWD" decimals="-3">636462000</tw-tse-pt:NonOperatingExpenses><tw-tse-pt:IncomeContinuingOperationsBeforeIncomeTax contextRef="From20040101To20040630" unitRef="TWD" decimals="-3">4123443000</tw-tse-pt:IncomeContinuingOperationsBeforeIncomeTax><tw-tse-pt:IncomeTaxExpense contextRef="From20040101To20040630" unitRef="TWD" decimals="-3">383038000</tw-tse-pt:IncomeTaxExpense><tw-tse-pt:IncomeContinuingOperations contextRef="From20040101To20040630" unitRef="TWD" decimals="-3">3740405000</tw-tse-pt:IncomeContinuingOperations><tw-tse-pt:NetIncomeLoss contextRef="From20040101To20040630" unitRef="TWD" decimals="-3">3740405000</tw-tse-pt:NetIncomeLoss><tw-tse-pt:PrimaryEarningsPerShare contextRef="From20040101To20040630" unitRef="EarningsPerShare" decimals="2">1.7</tw-tse-pt:PrimaryEarningsPerShare><tw-tse-pt:CashFlowOperatingActivities contextRef="From20040101To20040630" unitRef="TWD" decimals="-3">-5966013000</tw-tse-pt:CashFlowOperatingActivities><tw-tse-pt:CashFlowInvestingActivities contextRef="From20040101To20040630" unitRef="TWD" decimals="-3">-830895000</tw-tse-pt:CashFlowInvestingActivities><tw-tse-pt:CashFlowFinancingActivities contextRef="From20040101To20040630" unitRef="TWD" decimals="-3">6250204000</tw-tse-pt:CashFlowFinancingActivities><tw-tse-pt:NetCashFlow contextRef="From20040101To20040630" unitRef="TWD" decimals="-3">-546704000</tw-tse-pt:NetCashFlow><tw-tse-pt:Investments contextRef="AsOf20040630" unitRef="TWD" decimals="-3">32028580000</tw-tse-pt:Investments><tw-tse-pt:LongTermInvestmentsStocks contextRef="AsOf20040630" unitRef="TWD" decimals="-3">31399003000</tw-tse-pt:LongTermInvestmentsStocks><tw-tse-pt:PrepaymentsLongTermInvestmentsStocks contextRef="AsOf20040630" unitRef="TWD" decimals="-3">0</tw-tse-pt:PrepaymentsLongTermInvestmentsStocks><tw-tse-pt:OtherLongTermInvestments contextRef="AsOf20040630" unitRef="TWD" decimals="-3">629577000</tw-tse-pt:OtherLongTermInvestments><context id="From20040101To20040630"><entity><identifier scheme="http://www.tse.com.tw">2301</identifier></entity><period><startDate>2004-01-01</startDate><endDate>2004-06-30</endDate></period></context><context id="AsOf20040630"><entity><identifier scheme="http://www.tse.com.tw">2301</identifier></entity><period><instant>2004-06-30</instant></period></context><unit id="EarningsPerShare"><divide><unitNumerator><measure>iso4217:TWD</measure></unitNumerator><unitDenominator><measure>xbrli:shares</measure></unitDenominator></divide></unit><unit id="Shares"><measure>xbrli:shares</measure></unit><unit id="TWD"><measure>iso4217:TWD</measure></unit></xbrl>

