<?xml version="1.0"?>
<xbrl xmlns="http://www.xbrl.org/2003/instance" xmlns:xbrli="http://www.xbrl.org/2003/instance" xmlns:link="http://www.xbrl.org/2003/linkbase" xmlns:xlink="http://www.w3.org/1999/xlink" xmlns:iso4217="http://www.xbrl.org/2003/iso4217" xmlns:tw-tse-pt="http://www.tse.com.tw/tw/fr/gaap/2008-12-20"><link:schemaRef xlink:type="simple" xlink:arcrole="http://www.w3.org/1999/xlink/properties/linkbase" xlink:href="tw-tse-pt_2008-12-20.xsd"/><tw-tse-pt:CashCashEquivalents contextRef="AsOf20051231" unitRef="TWD" decimals="-3">4913923000</tw-tse-pt:CashCashEquivalents><tw-tse-pt:ShortTermInvestments contextRef="AsOf20051231" unitRef="TWD" decimals="-3">0</tw-tse-pt:ShortTermInvestments><tw-tse-pt:NetNotesReceivable contextRef="AsOf20051231" unitRef="TWD" decimals="-3">81698000</tw-tse-pt:NetNotesReceivable><tw-tse-pt:NetAccountsReceivable contextRef="AsOf20051231" unitRef="TWD" decimals="-3">8852651000</tw-tse-pt:NetAccountsReceivable><tw-tse-pt:NetAccountsReceivableRelatedParties contextRef="AsOf20051231" unitRef="TWD" decimals="-3">264863000</tw-tse-pt:NetAccountsReceivableRelatedParties><tw-tse-pt:OtherReceivables contextRef="AsOf20051231" unitRef="TWD" decimals="-3">3157876000</tw-tse-pt:OtherReceivables><tw-tse-pt:OtherReceivablesRelatedPartiesAfter2002 contextRef="AsOf20051231" unitRef="TWD" decimals="-3">291934000</tw-tse-pt:OtherReceivablesRelatedPartiesAfter2002><tw-tse-pt:Inventories contextRef="AsOf20051231" unitRef="TWD" decimals="-3">6166166000</tw-tse-pt:Inventories><tw-tse-pt:OtherCurrentAssets contextRef="AsOf20051231" unitRef="TWD" decimals="-3">1588400000</tw-tse-pt:OtherCurrentAssets><tw-tse-pt:CurrentAssets contextRef="AsOf20051231" unitRef="TWD" decimals="-3">25317511000</tw-tse-pt:CurrentAssets><tw-tse-pt:FundsInvestments contextRef="AsOf20051231" unitRef="TWD" decimals="-3">29921999000</tw-tse-pt:FundsInvestments><tw-tse-pt:Land contextRef="AsOf20051231" unitRef="TWD" decimals="-3">1558201000</tw-tse-pt:Land><tw-tse-pt:BuildingsStructures contextRef="AsOf20051231" unitRef="TWD" decimals="-3">14239471000</tw-tse-pt:BuildingsStructures><tw-tse-pt:MachineryEquipment contextRef="AsOf20051231" unitRef="TWD" decimals="-3">47931028000</tw-tse-pt:MachineryEquipment><tw-tse-pt:TransportationEquipment contextRef="AsOf20051231" unitRef="TWD" decimals="-3">68511000</tw-tse-pt:TransportationEquipment><tw-tse-pt:OfficeEquipment contextRef="AsOf20051231" unitRef="TWD" decimals="-3">974867000</tw-tse-pt:OfficeEquipment><tw-tse-pt:LeasedAssets contextRef="AsOf20051231" unitRef="TWD" decimals="-3">1469962000</tw-tse-pt:LeasedAssets><tw-tse-pt:FixedAssetsOriginalCosts contextRef="AsOf20051231" unitRef="TWD" decimals="-3">66242040000</tw-tse-pt:FixedAssetsOriginalCosts><tw-tse-pt:AccumulatedDepreciation contextRef="AsOf20051231" unitRef="TWD" decimals="-3">-32825973000</tw-tse-pt:AccumulatedDepreciation><tw-tse-pt:ConstructionProcessPrepaymentEquipments contextRef="AsOf20051231" unitRef="TWD" decimals="-3">3013450000</tw-tse-pt:ConstructionProcessPrepaymentEquipments><tw-tse-pt:FixedAssets contextRef="AsOf20051231" unitRef="TWD" decimals="-3">36429517000</tw-tse-pt:FixedAssets><tw-tse-pt:Goodwill contextRef="AsOf20051231" unitRef="TWD" decimals="-3">1380830000</tw-tse-pt:Goodwill><tw-tse-pt:IntangibleAssets contextRef="AsOf20051231" unitRef="TWD" decimals="-3">1380830000</tw-tse-pt:IntangibleAssets><tw-tse-pt:RentalAssets contextRef="AsOf20051231" unitRef="TWD" decimals="-3">0</tw-tse-pt:RentalAssets><tw-tse-pt:GuaranteeDepositsPaid contextRef="AsOf20051231" unitRef="TWD" decimals="-3">159659000</tw-tse-pt:GuaranteeDepositsPaid><tw-tse-pt:DeferredCharges contextRef="AsOf20051231" unitRef="TWD" decimals="-3">1495142000</tw-tse-pt:DeferredCharges><tw-tse-pt:DeferredIncomeTaxAssetsNonCurrent contextRef="AsOf20051231" unitRef="TWD" decimals="-3">2939964000</tw-tse-pt:DeferredIncomeTaxAssetsNonCurrent><tw-tse-pt:OtherAssetsOther contextRef="AsOf20051231" unitRef="TWD" decimals="-3">161510000</tw-tse-pt:OtherAssetsOther><tw-tse-pt:OtherAssets contextRef="AsOf20051231" unitRef="TWD" decimals="-3">4756275000</tw-tse-pt:OtherAssets><tw-tse-pt:Assets contextRef="AsOf20051231" unitRef="TWD" decimals="-3">97806132000</tw-tse-pt:Assets><tw-tse-pt:ShortTermBorrowings contextRef="AsOf20051231" unitRef="TWD" decimals="-3">2480008000</tw-tse-pt:ShortTermBorrowings><tw-tse-pt:AccountsPayable contextRef="AsOf20051231" unitRef="TWD" decimals="-3">7784399000</tw-tse-pt:AccountsPayable><tw-tse-pt:AccountsPayableRelatedParties contextRef="AsOf20051231" unitRef="TWD" decimals="-3">948080000</tw-tse-pt:AccountsPayableRelatedParties><tw-tse-pt:IncomeTaxPayable contextRef="AsOf20051231" unitRef="TWD" decimals="-3">15537000</tw-tse-pt:IncomeTaxPayable><tw-tse-pt:AccruedExpenses contextRef="AsOf20051231" unitRef="TWD" decimals="-3">2087615000</tw-tse-pt:AccruedExpenses><tw-tse-pt:OtherPayablesRelatedParties contextRef="AsOf20051231" unitRef="TWD" decimals="-3">678917000</tw-tse-pt:OtherPayablesRelatedParties><tw-tse-pt:OtherPayables contextRef="AsOf20051231" unitRef="TWD" decimals="-3">2561720000</tw-tse-pt:OtherPayables><tw-tse-pt:LongTermLiabilitiesCurrentPortion contextRef="AsOf20051231" unitRef="TWD" decimals="-3">2775290000</tw-tse-pt:LongTermLiabilitiesCurrentPortion><tw-tse-pt:OtherCurrentLiabilities contextRef="AsOf20051231" unitRef="TWD" decimals="-3">1283203000</tw-tse-pt:OtherCurrentLiabilities><tw-tse-pt:CurrentLiabilities contextRef="AsOf20051231" unitRef="TWD" decimals="-3">20614769000</tw-tse-pt:CurrentLiabilities><tw-tse-pt:BondsPayable contextRef="AsOf20051231" unitRef="TWD" decimals="-3">9361902000</tw-tse-pt:BondsPayable><tw-tse-pt:LongTermBorrowings contextRef="AsOf20051231" unitRef="TWD" decimals="-3">19495992000</tw-tse-pt:LongTermBorrowings><tw-tse-pt:LongTermNotesAccountsPayable contextRef="AsOf20051231" unitRef="TWD" decimals="-3">345668000</tw-tse-pt:LongTermNotesAccountsPayable><tw-tse-pt:LongTermLiabilities contextRef="AsOf20051231" unitRef="TWD" decimals="-3">29203562000</tw-tse-pt:LongTermLiabilities><tw-tse-pt:PensionReserve contextRef="AsOf20051231" unitRef="TWD" decimals="-3">751888000</tw-tse-pt:PensionReserve><tw-tse-pt:OtherLiabilitiesOther contextRef="AsOf20051231" unitRef="TWD" decimals="-3">158485000</tw-tse-pt:OtherLiabilitiesOther><tw-tse-pt:OtherLiabilities contextRef="AsOf20051231" unitRef="TWD" decimals="-3">910373000</tw-tse-pt:OtherLiabilities><tw-tse-pt:Liabilities contextRef="AsOf20051231" unitRef="TWD" decimals="-3">50728704000</tw-tse-pt:Liabilities><tw-tse-pt:CommonStock contextRef="AsOf20051231" unitRef="TWD" decimals="-3">45573723000</tw-tse-pt:CommonStock><tw-tse-pt:AdvanceReceiptsCommonStock contextRef="AsOf20051231" unitRef="TWD" decimals="-3">156228000</tw-tse-pt:AdvanceReceiptsCommonStock><tw-tse-pt:CapitalStock contextRef="AsOf20051231" unitRef="TWD" decimals="-3">45729951000</tw-tse-pt:CapitalStock><tw-tse-pt:CapitalSurplusAdditionalPaidCapital contextRef="AsOf20051231" unitRef="TWD" decimals="-3">2093712000</tw-tse-pt:CapitalSurplusAdditionalPaidCapital><tw-tse-pt:CapitalSurplusTreasuryStockTransactions contextRef="AsOf20051231" unitRef="TWD" decimals="-3">237503000</tw-tse-pt:CapitalSurplusTreasuryStockTransactions><tw-tse-pt:CapitalSurplusLongTermEquityInvestments contextRef="AsOf20051231" unitRef="TWD" decimals="-3">3585077000</tw-tse-pt:CapitalSurplusLongTermEquityInvestments><tw-tse-pt:CapitalSurplus contextRef="AsOf20051231" unitRef="TWD" decimals="-3">5916292000</tw-tse-pt:CapitalSurplus><tw-tse-pt:RetainedEarnings contextRef="AsOf20051231" unitRef="TWD" decimals="-3">-2745555000</tw-tse-pt:RetainedEarnings><tw-tse-pt:UnrealizedValuationLossesLongTermEquityInvestment contextRef="AsOf20051231" unitRef="TWD" decimals="-3">-69914000</tw-tse-pt:UnrealizedValuationLossesLongTermEquityInvestment><tw-tse-pt:CumulativeTranslationAdjustments contextRef="AsOf20051231" unitRef="TWD" decimals="-3">1072511000</tw-tse-pt:CumulativeTranslationAdjustments><tw-tse-pt:NetLossNotRecognizedPensionCost contextRef="AsOf20051231" unitRef="TWD" decimals="-3">-17421000</tw-tse-pt:NetLossNotRecognizedPensionCost><tw-tse-pt:UnrealizedGainsLossesFinancialInstrumentsSubsidiarySettled contextRef="AsOf20051231" unitRef="TWD" decimals="-3">0</tw-tse-pt:UnrealizedGainsLossesFinancialInstrumentsSubsidiarySettled><tw-tse-pt:StockholdersEquitiesAdjustments contextRef="AsOf20051231" unitRef="TWD" decimals="-3">985176000</tw-tse-pt:StockholdersEquitiesAdjustments><tw-tse-pt:TreasuryStock contextRef="AsOf20051231" unitRef="TWD" decimals="-3">-2808436000</tw-tse-pt:TreasuryStock><tw-tse-pt:StockholdersEquities contextRef="AsOf20051231" unitRef="TWD" decimals="-3">47077428000</tw-tse-pt:StockholdersEquities><tw-tse-pt:NumberTreasuryStockAcquiredCompanySubsidiaries contextRef="AsOf20051231" unitRef="Shares" decimals="0">184713372</tw-tse-pt:NumberTreasuryStockAcquiredCompanySubsidiaries><tw-tse-pt:OperatingIncome contextRef="From20050101To20051231" unitRef="TWD" decimals="-3">53523704000</tw-tse-pt:OperatingIncome><tw-tse-pt:NetSales contextRef="From20050101To20051231" unitRef="TWD" decimals="-3">53523704000</tw-tse-pt:NetSales><tw-tse-pt:Sales contextRef="From20050101To20051231" unitRef="TWD" decimals="-3">54200019000</tw-tse-pt:Sales><tw-tse-pt:SalesDiscountsAllowances contextRef="From20050101To20051231" unitRef="TWD" decimals="-3">676315000</tw-tse-pt:SalesDiscountsAllowances><tw-tse-pt:OperatingCosts contextRef="From20050101To20051231" unitRef="TWD" decimals="-3">45016287000</tw-tse-pt:OperatingCosts><tw-tse-pt:GrossProfitLossOperations contextRef="From20050101To20051231" unitRef="TWD" decimals="-3">8507417000</tw-tse-pt:GrossProfitLossOperations><tw-tse-pt:Sellingexpense contextRef="From20050101To20051231" unitRef="TWD" decimals="-3">941590000</tw-tse-pt:Sellingexpense><tw-tse-pt:GeneralAdministrativeExpenses contextRef="From20050101To20051231" unitRef="TWD" decimals="-3">1902755000</tw-tse-pt:GeneralAdministrativeExpenses><tw-tse-pt:ResearchDevelopmentExpenses contextRef="From20050101To20051231" unitRef="TWD" decimals="-3">1595342000</tw-tse-pt:ResearchDevelopmentExpenses><tw-tse-pt:OperatingExpenses contextRef="From20050101To20051231" unitRef="TWD" decimals="-3">4439687000</tw-tse-pt:OperatingExpenses><tw-tse-pt:OperatingIncomeLoss contextRef="From20050101To20051231" unitRef="TWD" decimals="-3">4067730000</tw-tse-pt:OperatingIncomeLoss><tw-tse-pt:InterestIncome contextRef="From20050101To20051231" unitRef="TWD" decimals="-3">82456000</tw-tse-pt:InterestIncome><tw-tse-pt:ForeignExchangeGains contextRef="From20050101To20051231" unitRef="TWD" decimals="-3">86493000</tw-tse-pt:ForeignExchangeGains><tw-tse-pt:MiscellaneousIncome contextRef="From20050101To20051231" unitRef="TWD" decimals="-3">291308000</tw-tse-pt:MiscellaneousIncome><tw-tse-pt:NonOperatingRevenuesGains contextRef="From20050101To20051231" unitRef="TWD" decimals="-3">460257000</tw-tse-pt:NonOperatingRevenuesGains><tw-tse-pt:InterestExpense contextRef="From20050101To20051231" unitRef="TWD" decimals="-3">991591000</tw-tse-pt:InterestExpense><tw-tse-pt:InvestmentLoss contextRef="From20050101To20051231" unitRef="TWD" decimals="-3">55895000</tw-tse-pt:InvestmentLoss><tw-tse-pt:MiscellaneousDisbursements contextRef="From20050101To20051231" unitRef="TWD" decimals="-3">8845719000</tw-tse-pt:MiscellaneousDisbursements><tw-tse-pt:NonOperatingExpenses contextRef="From20050101To20051231" unitRef="TWD" decimals="-3">9893205000</tw-tse-pt:NonOperatingExpenses><tw-tse-pt:IncomeContinuingOperationsBeforeIncomeTax contextRef="From20050101To20051231" unitRef="TWD" decimals="-3">-5365218000</tw-tse-pt:IncomeContinuingOperationsBeforeIncomeTax><tw-tse-pt:IncomeTaxExpense contextRef="From20050101To20051231" unitRef="TWD" decimals="-3">-674031000</tw-tse-pt:IncomeTaxExpense><tw-tse-pt:IncomeContinuingOperations contextRef="From20050101To20051231" unitRef="TWD" decimals="-3">-4691187000</tw-tse-pt:IncomeContinuingOperations><tw-tse-pt:CumulativeEffectChangesAccountingPrinciple contextRef="From20050101To20051231" unitRef="TWD" decimals="-3">0</tw-tse-pt:CumulativeEffectChangesAccountingPrinciple><tw-tse-pt:NetIncomeLoss contextRef="From20050101To20051231" unitRef="TWD" decimals="-3">-4691187000</tw-tse-pt:NetIncomeLoss><tw-tse-pt:PrimaryEarningsPerShare contextRef="From20050101To20051231" unitRef="EarningsPerShare" decimals="2">-1.07</tw-tse-pt:PrimaryEarningsPerShare><tw-tse-pt:FullDilutedEarningsPerShare contextRef="From20050101To20051231" unitRef="EarningsPerShare" decimals="2">-1.07</tw-tse-pt:FullDilutedEarningsPerShare><tw-tse-pt:CashFlowOperatingActivities contextRef="From20050101To20051231" unitRef="TWD" decimals="-3">12117856000</tw-tse-pt:CashFlowOperatingActivities><tw-tse-pt:CashFlowInvestingActivities contextRef="From20050101To20051231" unitRef="TWD" decimals="-3">-8752489000</tw-tse-pt:CashFlowInvestingActivities><tw-tse-pt:CashFlowFinancingActivities contextRef="From20050101To20051231" unitRef="TWD" decimals="-3">-1370504000</tw-tse-pt:CashFlowFinancingActivities><tw-tse-pt:EffectsExchangeRateChanges contextRef="From20050101To20051231" unitRef="TWD" decimals="-3">-48574000</tw-tse-pt:EffectsExchangeRateChanges><tw-tse-pt:NetCashFlow contextRef="From20050101To20051231" unitRef="TWD" decimals="-3">1946289000</tw-tse-pt:NetCashFlow><tw-tse-pt:Investments contextRef="AsOf20051231" unitRef="TWD" decimals="-3">29921999000</tw-tse-pt:Investments><tw-tse-pt:LongTermInvestmentsStocks contextRef="AsOf20051231" unitRef="TWD" decimals="-3">29863916000</tw-tse-pt:LongTermInvestmentsStocks><tw-tse-pt:PrepaymentsLongTermInvestmentsStocks contextRef="AsOf20051231" unitRef="TWD" decimals="-3">8083000</tw-tse-pt:PrepaymentsLongTermInvestmentsStocks><tw-tse-pt:OtherLongTermInvestments contextRef="AsOf20051231" unitRef="TWD" decimals="-3">50000000</tw-tse-pt:OtherLongTermInvestments><context id="From20050101To20051231"><entity><identifier scheme="http://www.tse.com.tw">2311</identifier></entity><period><startDate>2005-01-01</startDate><endDate>2005-12-31</endDate></period></context><context id="AsOf20051231"><entity><identifier scheme="http://www.tse.com.tw">2311</identifier></entity><period><instant>2005-12-31</instant></period></context><unit id="EarningsPerShare"><divide><unitNumerator><measure>iso4217:TWD</measure></unitNumerator><unitDenominator><measure>xbrli:shares</measure></unitDenominator></divide></unit><unit id="Shares"><measure>xbrli:shares</measure></unit><unit id="TWD"><measure>iso4217:TWD</measure></unit></xbrl>

