<?xml version="1.0"?>
<xbrl xmlns="http://www.xbrl.org/2003/instance" xmlns:xbrli="http://www.xbrl.org/2003/instance" xmlns:link="http://www.xbrl.org/2003/linkbase" xmlns:xlink="http://www.w3.org/1999/xlink" xmlns:iso4217="http://www.xbrl.org/2003/iso4217" xmlns:tw-tse-pt="http://www.tse.com.tw/tw/fr/gaap/2008-12-20"><link:schemaRef xlink:type="simple" xlink:arcrole="http://www.w3.org/1999/xlink/properties/linkbase" xlink:href="tw-tse-pt_2008-12-20.xsd"/><tw-tse-pt:CashCashEquivalents contextRef="AsOf20080331" unitRef="TWD" decimals="-3">16318003000</tw-tse-pt:CashCashEquivalents><tw-tse-pt:FinancialAssetsMeasuredFairValueProfitLossCurrent contextRef="AsOf20080331" unitRef="TWD" decimals="-3">315376000</tw-tse-pt:FinancialAssetsMeasuredFairValueProfitLossCurrent><tw-tse-pt:AvailableSaleFinancialAssetsCurrent contextRef="AsOf20080331" unitRef="TWD" decimals="-3">1091910000</tw-tse-pt:AvailableSaleFinancialAssetsCurrent><tw-tse-pt:NetAccountsReceivable contextRef="AsOf20080331" unitRef="TWD" decimals="-3">106396876000</tw-tse-pt:NetAccountsReceivable><tw-tse-pt:NetAccountsReceivableRelatedParties contextRef="AsOf20080331" unitRef="TWD" decimals="-3">21329823000</tw-tse-pt:NetAccountsReceivableRelatedParties><tw-tse-pt:OtherReceivables contextRef="AsOf20080331" unitRef="TWD" decimals="-3">20410687000</tw-tse-pt:OtherReceivables><tw-tse-pt:Inventories contextRef="AsOf20080331" unitRef="TWD" decimals="-3">91759913000</tw-tse-pt:Inventories><tw-tse-pt:OtherPrepayments contextRef="AsOf20080331" unitRef="TWD" decimals="-3">25723473000</tw-tse-pt:OtherPrepayments><tw-tse-pt:OtherCurrentAssets contextRef="AsOf20080331" unitRef="TWD" decimals="-3">2634154000</tw-tse-pt:OtherCurrentAssets><tw-tse-pt:CurrentAssets contextRef="AsOf20080331" unitRef="TWD" decimals="-3">285980215000</tw-tse-pt:CurrentAssets><tw-tse-pt:NetAvailablesaleFinancialAssetsNonCurrent contextRef="AsOf20080331" unitRef="TWD" decimals="-3">9133086000</tw-tse-pt:NetAvailablesaleFinancialAssetsNonCurrent><tw-tse-pt:NetFinancialAssetsCarriedCostNonCurrent contextRef="AsOf20080331" unitRef="TWD" decimals="-3">531806000</tw-tse-pt:NetFinancialAssetsCarriedCostNonCurrent><tw-tse-pt:OtherFinancialAssetsNonCurrent contextRef="AsOf20080331" unitRef="TWD" decimals="-3">90384000</tw-tse-pt:OtherFinancialAssetsNonCurrent><tw-tse-pt:FundsInvestments contextRef="AsOf20080331" unitRef="TWD" decimals="-3">262572690000</tw-tse-pt:FundsInvestments><tw-tse-pt:Land contextRef="AsOf20080331" unitRef="TWD" decimals="-3">1671640000</tw-tse-pt:Land><tw-tse-pt:BuildingsStructures contextRef="AsOf20080331" unitRef="TWD" decimals="-3">3412251000</tw-tse-pt:BuildingsStructures><tw-tse-pt:MachineryEquipment contextRef="AsOf20080331" unitRef="TWD" decimals="-3">47196775000</tw-tse-pt:MachineryEquipment><tw-tse-pt:MoldingEquipment contextRef="AsOf20080331" unitRef="TWD" decimals="-3">1701214000</tw-tse-pt:MoldingEquipment><tw-tse-pt:TestingEquipment contextRef="AsOf20080331" unitRef="TWD" decimals="-3">7574490000</tw-tse-pt:TestingEquipment><tw-tse-pt:OfficeEquipment contextRef="AsOf20080331" unitRef="TWD" decimals="-3">1348972000</tw-tse-pt:OfficeEquipment><tw-tse-pt:MaintenanceEquipmentTools contextRef="AsOf20080331" unitRef="TWD" decimals="-3">539628000</tw-tse-pt:MaintenanceEquipmentTools><tw-tse-pt:OtherFacilities contextRef="AsOf20080331" unitRef="TWD" decimals="-3">1786101000</tw-tse-pt:OtherFacilities><tw-tse-pt:FixedAssetsOriginalCosts contextRef="AsOf20080331" unitRef="TWD" decimals="-3">65231071000</tw-tse-pt:FixedAssetsOriginalCosts><tw-tse-pt:AccumulatedDepreciation contextRef="AsOf20080331" unitRef="TWD" decimals="-3">-30030891000</tw-tse-pt:AccumulatedDepreciation><tw-tse-pt:ConstructionProcessPrepaymentEquipments contextRef="AsOf20080331" unitRef="TWD" decimals="-3">2696702000</tw-tse-pt:ConstructionProcessPrepaymentEquipments><tw-tse-pt:FixedAssets contextRef="AsOf20080331" unitRef="TWD" decimals="-3">37896882000</tw-tse-pt:FixedAssets><tw-tse-pt:DeferredCharges contextRef="AsOf20080331" unitRef="TWD" decimals="-3">726528000</tw-tse-pt:DeferredCharges><tw-tse-pt:OtherAssetsOther contextRef="AsOf20080331" unitRef="TWD" decimals="-3">506245000</tw-tse-pt:OtherAssetsOther><tw-tse-pt:OtherAssets contextRef="AsOf20080331" unitRef="TWD" decimals="-3">1232773000</tw-tse-pt:OtherAssets><tw-tse-pt:Assets contextRef="AsOf20080331" unitRef="TWD" decimals="-3">587682560000</tw-tse-pt:Assets><tw-tse-pt:ShortTermBorrowings contextRef="AsOf20080331" unitRef="TWD" decimals="-3">39049712000</tw-tse-pt:ShortTermBorrowings><tw-tse-pt:FinancialLiabilitiesMeasuredFairValueProfitLossCurrent contextRef="AsOf20080331" unitRef="TWD" decimals="-3">20241000</tw-tse-pt:FinancialLiabilitiesMeasuredFairValueProfitLossCurrent><tw-tse-pt:AccountsPayable contextRef="AsOf20080331" unitRef="TWD" decimals="-3">96323512000</tw-tse-pt:AccountsPayable><tw-tse-pt:AccountsPayableRelatedParties contextRef="AsOf20080331" unitRef="TWD" decimals="-3">17991458000</tw-tse-pt:AccountsPayableRelatedParties><tw-tse-pt:IncomeTaxPayable contextRef="AsOf20080331" unitRef="TWD" decimals="-3">10056888000</tw-tse-pt:IncomeTaxPayable><tw-tse-pt:AccruedExpenses contextRef="AsOf20080331" unitRef="TWD" decimals="-3">12369582000</tw-tse-pt:AccruedExpenses><tw-tse-pt:OtherPayables contextRef="AsOf20080331" unitRef="TWD" decimals="-3">18564609000</tw-tse-pt:OtherPayables><tw-tse-pt:OtherCurrentLiabilities contextRef="AsOf20080331" unitRef="TWD" decimals="-3">3933611000</tw-tse-pt:OtherCurrentLiabilities><tw-tse-pt:CurrentLiabilities contextRef="AsOf20080331" unitRef="TWD" decimals="-3">198309613000</tw-tse-pt:CurrentLiabilities><tw-tse-pt:BondsPayable contextRef="AsOf20080331" unitRef="TWD" decimals="-3">28858194000</tw-tse-pt:BondsPayable><tw-tse-pt:LongTermLiabilities contextRef="AsOf20080331" unitRef="TWD" decimals="-3">28858194000</tw-tse-pt:LongTermLiabilities><tw-tse-pt:PensionReserve contextRef="AsOf20080331" unitRef="TWD" decimals="-3">797610000</tw-tse-pt:PensionReserve><tw-tse-pt:DeferredIncomeTax contextRef="AsOf20080331" unitRef="TWD" decimals="-3">9116206000</tw-tse-pt:DeferredIncomeTax><tw-tse-pt:OtherLiabilitiesOther contextRef="AsOf20080331" unitRef="TWD" decimals="-3">173682000</tw-tse-pt:OtherLiabilitiesOther><tw-tse-pt:OtherLiabilities contextRef="AsOf20080331" unitRef="TWD" decimals="-3">10087498000</tw-tse-pt:OtherLiabilities><tw-tse-pt:Liabilities contextRef="AsOf20080331" unitRef="TWD" decimals="-3">237255305000</tw-tse-pt:Liabilities><tw-tse-pt:CommonStock contextRef="AsOf20080331" unitRef="TWD" decimals="-3">62907666000</tw-tse-pt:CommonStock><tw-tse-pt:CapitalStock contextRef="AsOf20080331" unitRef="TWD" decimals="-3">62907666000</tw-tse-pt:CapitalStock><tw-tse-pt:CapitalSurplusAdditionalPaidCapital contextRef="AsOf20080331" unitRef="TWD" decimals="-3">38704298000</tw-tse-pt:CapitalSurplusAdditionalPaidCapital><tw-tse-pt:CapitalSurplusLongTermEquityInvestments contextRef="AsOf20080331" unitRef="TWD" decimals="-3">13073531000</tw-tse-pt:CapitalSurplusLongTermEquityInvestments><tw-tse-pt:CapitalSurplus contextRef="AsOf20080331" unitRef="TWD" decimals="-3">52973029000</tw-tse-pt:CapitalSurplus><tw-tse-pt:LegalReserve contextRef="AsOf20080331" unitRef="TWD" decimals="-3">23255167000</tw-tse-pt:LegalReserve><tw-tse-pt:UnappropriatedRetainedEarnings contextRef="AsOf20080331" unitRef="TWD" decimals="-3">180532165000</tw-tse-pt:UnappropriatedRetainedEarnings><tw-tse-pt:RetainedEarnings contextRef="AsOf20080331" unitRef="TWD" decimals="-3">203787332000</tw-tse-pt:RetainedEarnings><tw-tse-pt:CumulativeTranslationAdjustments contextRef="AsOf20080331" unitRef="TWD" decimals="-3">3429205000</tw-tse-pt:CumulativeTranslationAdjustments><tw-tse-pt:UnrealizedGainsLossesFinancialInstruments contextRef="AsOf20080331" unitRef="TWD" decimals="-3">27348924000</tw-tse-pt:UnrealizedGainsLossesFinancialInstruments><tw-tse-pt:StockholdersEquitiesAdjustments contextRef="AsOf20080331" unitRef="TWD" decimals="-3">30778129000</tw-tse-pt:StockholdersEquitiesAdjustments><tw-tse-pt:TreasuryStock contextRef="AsOf20080331" unitRef="TWD" decimals="-3">-18901000</tw-tse-pt:TreasuryStock><tw-tse-pt:StockholdersEquities contextRef="AsOf20080331" unitRef="TWD" decimals="-3">350427255000</tw-tse-pt:StockholdersEquities><tw-tse-pt:NumberTreasuryStockAcquiredCompanySubsidiaries contextRef="AsOf20080331" unitRef="Shares" decimals="0">726915</tw-tse-pt:NumberTreasuryStockAcquiredCompanySubsidiaries><tw-tse-pt:OperatingIncome contextRef="From20080101To20080331" unitRef="TWD" decimals="-3">301803472000</tw-tse-pt:OperatingIncome><tw-tse-pt:NetSales contextRef="From20080101To20080331" unitRef="TWD" decimals="-3">301803472000</tw-tse-pt:NetSales><tw-tse-pt:Sales contextRef="From20080101To20080331" unitRef="TWD" decimals="-3">301817102000</tw-tse-pt:Sales><tw-tse-pt:SalesReturns contextRef="From20080101To20080331" unitRef="TWD" decimals="-3">0</tw-tse-pt:SalesReturns><tw-tse-pt:SalesDiscountsAllowances contextRef="From20080101To20080331" unitRef="TWD" decimals="-3">13630000</tw-tse-pt:SalesDiscountsAllowances><tw-tse-pt:CostSales contextRef="From20080101To20080331" unitRef="TWD" decimals="-3">287241272000</tw-tse-pt:CostSales><tw-tse-pt:OperatingCosts contextRef="From20080101To20080331" unitRef="TWD" decimals="-3">287241272000</tw-tse-pt:OperatingCosts><tw-tse-pt:GrossProfitLossOperations contextRef="From20080101To20080331" unitRef="TWD" decimals="-3">14562200000</tw-tse-pt:GrossProfitLossOperations><tw-tse-pt:Sellingexpense contextRef="From20080101To20080331" unitRef="TWD" decimals="-3">3737714000</tw-tse-pt:Sellingexpense><tw-tse-pt:GeneralAdministrativeExpenses contextRef="From20080101To20080331" unitRef="TWD" decimals="-3">1226124000</tw-tse-pt:GeneralAdministrativeExpenses><tw-tse-pt:ResearchDevelopmentExpenses contextRef="From20080101To20080331" unitRef="TWD" decimals="-3">2345457000</tw-tse-pt:ResearchDevelopmentExpenses><tw-tse-pt:OperatingExpenses contextRef="From20080101To20080331" unitRef="TWD" decimals="-3">7309295000</tw-tse-pt:OperatingExpenses><tw-tse-pt:OperatingIncomeLoss contextRef="From20080101To20080331" unitRef="TWD" decimals="-3">7252905000</tw-tse-pt:OperatingIncomeLoss><tw-tse-pt:InterestIncome contextRef="From20080101To20080331" unitRef="TWD" decimals="-3">39898000</tw-tse-pt:InterestIncome><tw-tse-pt:InvestmentIncomes contextRef="From20080101To20080331" unitRef="TWD" decimals="-3">11479008000</tw-tse-pt:InvestmentIncomes><tw-tse-pt:ForeignExchangeGains contextRef="From20080101To20080331" unitRef="TWD" decimals="-3">47046000</tw-tse-pt:ForeignExchangeGains><tw-tse-pt:RevaluationGainFinancialAssets contextRef="From20080101To20080331" unitRef="TWD" decimals="-3">263685000</tw-tse-pt:RevaluationGainFinancialAssets><tw-tse-pt:RevaluationGainFinancialLiabilities contextRef="From20080101To20080331" unitRef="TWD" decimals="-3">0</tw-tse-pt:RevaluationGainFinancialLiabilities><tw-tse-pt:MiscellaneousIncome contextRef="From20080101To20080331" unitRef="TWD" decimals="-3">175875000</tw-tse-pt:MiscellaneousIncome><tw-tse-pt:NonOperatingRevenuesGains contextRef="From20080101To20080331" unitRef="TWD" decimals="-3">12005512000</tw-tse-pt:NonOperatingRevenuesGains><tw-tse-pt:InterestExpense contextRef="From20080101To20080331" unitRef="TWD" decimals="-3">483281000</tw-tse-pt:InterestExpense><tw-tse-pt:ForeignExchangeLosses contextRef="From20080101To20080331" unitRef="TWD" decimals="-3">0</tw-tse-pt:ForeignExchangeLosses><tw-tse-pt:RevaluationLossFinancialAssets contextRef="From20080101To20080331" unitRef="TWD" decimals="-3">0</tw-tse-pt:RevaluationLossFinancialAssets><tw-tse-pt:RevaluationLossFinancialLiabilities contextRef="From20080101To20080331" unitRef="TWD" decimals="-3">41034000</tw-tse-pt:RevaluationLossFinancialLiabilities><tw-tse-pt:MiscellaneousDisbursements contextRef="From20080101To20080331" unitRef="TWD" decimals="-3">324098000</tw-tse-pt:MiscellaneousDisbursements><tw-tse-pt:NonOperatingExpenses contextRef="From20080101To20080331" unitRef="TWD" decimals="-3">848413000</tw-tse-pt:NonOperatingExpenses><tw-tse-pt:IncomeContinuingOperationsBeforeIncomeTax contextRef="From20080101To20080331" unitRef="TWD" decimals="-3">18410004000</tw-tse-pt:IncomeContinuingOperationsBeforeIncomeTax><tw-tse-pt:IncomeTaxExpense contextRef="From20080101To20080331" unitRef="TWD" decimals="-3">2335838000</tw-tse-pt:IncomeTaxExpense><tw-tse-pt:IncomeContinuingOperations contextRef="From20080101To20080331" unitRef="TWD" decimals="-3">16074166000</tw-tse-pt:IncomeContinuingOperations><tw-tse-pt:NetIncomeLoss contextRef="From20080101To20080331" unitRef="TWD" decimals="-3">16074166000</tw-tse-pt:NetIncomeLoss><tw-tse-pt:PrimaryEarningsPerShare contextRef="From20080101To20080331" unitRef="EarningsPerShare" decimals="2">2.56</tw-tse-pt:PrimaryEarningsPerShare><tw-tse-pt:PrimaryEarningsPerShareIncomeLossContinuingOperations contextRef="From20080101To20080331" unitRef="EarningsPerShare" decimals="2">2.56</tw-tse-pt:PrimaryEarningsPerShareIncomeLossContinuingOperations><tw-tse-pt:FullDilutedEarningsPerShare contextRef="From20080101To20080331" unitRef="EarningsPerShare" decimals="2">2.54</tw-tse-pt:FullDilutedEarningsPerShare><tw-tse-pt:FullDilutedEarningsPerShareIncomeLossDiscontinuedOperations contextRef="From20080101To20080331" unitRef="EarningsPerShare" decimals="2">2.54</tw-tse-pt:FullDilutedEarningsPerShareIncomeLossDiscontinuedOperations><tw-tse-pt:CashFlowOperatingActivities contextRef="From20080101To20080331" unitRef="TWD" decimals="-3">12742954000</tw-tse-pt:CashFlowOperatingActivities><tw-tse-pt:CashFlowInvestingActivities contextRef="From20080101To20080331" unitRef="TWD" decimals="-3">-7510919000</tw-tse-pt:CashFlowInvestingActivities><tw-tse-pt:CashFlowFinancingActivities contextRef="From20080101To20080331" unitRef="TWD" decimals="-3">3999287000</tw-tse-pt:CashFlowFinancingActivities><tw-tse-pt:NetCashFlow contextRef="From20080101To20080331" unitRef="TWD" decimals="-3">9231322000</tw-tse-pt:NetCashFlow><tw-tse-pt:StockOption contextRef="AsOf20080331" unitRef="TWD" decimals="-3">1195200000</tw-tse-pt:StockOption><tw-tse-pt:Investments contextRef="AsOf20080331" unitRef="TWD" decimals="-3">252817414000</tw-tse-pt:Investments><tw-tse-pt:LongTermInvestmentsStocks contextRef="AsOf20080331" unitRef="TWD" decimals="-3">251427335000</tw-tse-pt:LongTermInvestmentsStocks><tw-tse-pt:PrepaymentsLongTermInvestmentsStocks contextRef="AsOf20080331" unitRef="TWD" decimals="-3">1390079000</tw-tse-pt:PrepaymentsLongTermInvestmentsStocks><context id="From20080101To20080331"><entity><identifier scheme="http://www.tse.com.tw">2317</identifier></entity><period><startDate>2008-01-01</startDate><endDate>2008-03-31</endDate></period></context><context id="AsOf20080331"><entity><identifier scheme="http://www.tse.com.tw">2317</identifier></entity><period><instant>2008-03-31</instant></period></context><unit id="EarningsPerShare"><divide><unitNumerator><measure>iso4217:TWD</measure></unitNumerator><unitDenominator><measure>xbrli:shares</measure></unitDenominator></divide></unit><unit id="Shares"><measure>xbrli:shares</measure></unit><unit id="TWD"><measure>iso4217:TWD</measure></unit></xbrl>

